geci_mimesis/__init__.py
geci_mimesis/generate_single_value.py
geci_mimesis-0.5.0.dist-info/LICENSE
geci_mimesis-0.5.0.dist-info/WHEEL
geci_mimesis-0.5.0.dist-info/METADATA
geci_mimesis-0.5.0.dist-info/RECORD
