Metadata-Version: 2.1
Name: geci_mimesis
Version: 0.5.0
Summary: A template Python module
Home-page: https://github.com/IslasGECI/geci_mimesis
Author: Ciencia de Datos • GECI
Author-email: ciencia.datos@islas.org.mx
Requires-Python: >=3.9
Classifier: License :: OSI Approved :: GNU General Public License v3 or later (GPLv3+)
Requires-Dist: mimesis
